life_fighter/__init__.py
life_fighter/data/cells/conway/Baliza.pat
life_fighter/data/cells/conway/Barcaza larga.pat
life_fighter/data/cells/conway/Barcaza.pat
life_fighter/data/cells/conway/Barco largo.pat
life_fighter/data/cells/conway/Barco.pat
life_fighter/data/cells/conway/Bloque.pat
life_fighter/data/cells/conway/Bote largo.pat
life_fighter/data/cells/conway/Bote.pat
life_fighter/data/cells/conway/Canion.pat.big
life_fighter/data/cells/conway/Charca.pat
life_fighter/data/cells/conway/Cifra 8.pat
life_fighter/data/cells/conway/Colmena.pat
life_fighter/data/cells/conway/Colmenar.pat
life_fighter/data/cells/conway/Cruz latina.pat
life_fighter/data/cells/conway/Deslizador.pat
life_fighter/data/cells/conway/Hogaza.pat
life_fighter/data/cells/conway/Intermitente.pat
life_fighter/data/cells/conway/Letra H.pat
life_fighter/data/cells/conway/Molino.pat
life_fighter/data/cells/conway/Reloj.pat
life_fighter/data/cells/conway/Sapo.pat
life_fighter/data/cells/conway/Serpiente.pat
life_fighter/data/cells/conway/Tina.pat
life_fighter/data/cells/games/car.pob
life_fighter/data/cells/games/dispar.pob
life_fighter/data/cells/games/eyes.pob
life_fighter/data/cells/games/first.pob
life_fighter/data/cells/games/rombo.pob
life_fighter/data/cells/games/simple01.pob
life_fighter/data/cells/games/simple02.pob
life_fighter/data/cells/games/simple03.pob
life_fighter/data/cells/games/simple04.pob
life_fighter/data/cells/games/simple05.pob
life_fighter/data/cells/games/simplest.pob
life_fighter/data/cells/games/smile.pob
life_fighter/data/cells/games/sun.pob
life_fighter/data/cells/games/triangle.pob
life_fighter/data/fonts/B52.ttf
life_fighter/data/fonts/FreeMono.ttf
life_fighter/data/fonts/FreeMonoBold.ttf
life_fighter/data/fonts/FreeMonoBoldOblique.ttf
life_fighter/data/fonts/FreeMonoOblique.ttf
life_fighter/data/fonts/FreeSans.ttf
life_fighter/data/fonts/FreeSansBold.ttf
life_fighter/data/fonts/FreeSansBoldOblique.ttf
life_fighter/data/fonts/FreeSansOblique.ttf
life_fighter-0.2.dist-info/WHEEL
life_fighter-0.2.dist-info/METADATA
life_fighter-0.2.dist-info/RECORD
